xboing/__init__.py
xboing/__main__.py
xboing/__version__.py
xboing/app_coordinator.py
xboing/di_module.py
xboing/py.typed
xboing/xboing.py
xboing/assets/config/block_types.json
xboing/assets/images/floppy.png
xboing/assets/images/highscr.png
xboing/assets/images/icon.png
xboing/assets/images/larrow.png
xboing/assets/images/mouse.png
xboing/assets/images/question.png
xboing/assets/images/rarrow.png
xboing/assets/images/text.png
xboing/assets/images/xboing.png
xboing/assets/images/xboing_docs_logo.png
xboing/assets/images/balls/ball1.png
xboing/assets/images/balls/ball2.png
xboing/assets/images/balls/ball3.png
xboing/assets/images/balls/ball4.png
xboing/assets/images/balls/bbirth1.png
xboing/assets/images/balls/bbirth2.png
xboing/assets/images/balls/bbirth3.png
xboing/assets/images/balls/bbirth4.png
xboing/assets/images/balls/bbirth5.png
xboing/assets/images/balls/bbirth6.png
xboing/assets/images/balls/bbirth7.png
xboing/assets/images/balls/bbirth8.png
xboing/assets/images/balls/killer.png
xboing/assets/images/balls/life.png
xboing/assets/images/bgrnds/bgrnd.png
xboing/assets/images/bgrnds/bgrnd2.png
xboing/assets/images/bgrnds/bgrnd3.png
xboing/assets/images/bgrnds/bgrnd4.png
xboing/assets/images/bgrnds/bgrnd5.png
xboing/assets/images/bgrnds/mnbgrnd.png
xboing/assets/images/bgrnds/space.png
xboing/assets/images/blocks/blakblk.png
xboing/assets/images/blocks/blakblkH.png
xboing/assets/images/blocks/bltblk.png
xboing/assets/images/blocks/blueblk.png
xboing/assets/images/blocks/bombblk.png
xboing/assets/images/blocks/bonus1.png
xboing/assets/images/blocks/bonus2.png
xboing/assets/images/blocks/bonus3.png
xboing/assets/images/blocks/bonus4.png
xboing/assets/images/blocks/clock.png
xboing/assets/images/blocks/cntblk.png
xboing/assets/images/blocks/cntblk1.png
xboing/assets/images/blocks/cntblk2.png
xboing/assets/images/blocks/cntblk3.png
xboing/assets/images/blocks/cntblk4.png
xboing/assets/images/blocks/cntblk5.png
xboing/assets/images/blocks/death1.png
xboing-0.4.0.dist-info/METADATA
xboing-0.4.0.dist-info/WHEEL
xboing-0.4.0.dist-info/entry_points.txt
xboing-0.4.0.dist-info/licenses/LICENSE
xboing-0.4.0.dist-info/RECORD
