Metadata-Version: 2.4
Name: xboing
Version: 0.4.0
Summary: XBoing - A classic breakout-style game modernized with Python and Pygame
Project-URL: Homepage, https://github.com/jmf-pobox/xboing-python
Project-URL: Bug Tracker, https://github.com/jmf-pobox/xboing-python/issues
Author: Original: Justin C. Kibell, Python port: XBoing-py Team
License: X Consortium License
License-File: LICENSE
Classifier: Development Status :: 3 - Alpha
Classifier: Intended Audience :: End Users/Desktop
Classifier: License :: OSI Approved :: MIT License
Classifier: Operating System :: OS Independent
Classifier: Programming Language :: Python :: 3
Classifier: Programming Language :: Python :: 3.10
Classifier: Programming Language :: Python :: 3.11
Classifier: Programming Language :: Python :: 3.12
Classifier: Topic :: Games/Entertainment :: Arcade
Requires-Python: >=3.10
Requires-Dist: injector>=0.21.0
Requires-Dist: pygame
Requires-Dist: typing-extensions
